tinyros/__init__.py
tinyros/node.py
tinyros-0.2.2.dist-info/licenses/LICENSE
tinyros-0.2.2.dist-info/METADATA
tinyros-0.2.2.dist-info/WHEEL
tinyros-0.2.2.dist-info/top_level.txt
tinyros-0.2.2.dist-info/RECORD
