Metadata-Version: 2.4
Name: tinyros
Version: 0.2.2
Summary: A minimal operating system for robotics.
Author-email: Antonio Terpin <aterpin@ethz.ch>
License: MIT
Project-URL: Homepage, https://github.com/antonioterpin/tinyros
Classifier: Programming Language :: Python :: 3
Classifier: License :: OSI Approved :: MIT License
Classifier: Operating System :: OS Independent
Requires-Python: >=3.10
License-File: LICENSE
Requires-Dist: portal>=0.1.0
Requires-Dist: PyYAML>=6.0.0
Provides-Extra: dev
Requires-Dist: pytest>=7.0.0; extra == "dev"
Requires-Dist: pytest-cov>=4.0.0; extra == "dev"
Requires-Dist: hypothesis>=6.0.0; extra == "dev"
Requires-Dist: snowballstemmer==2.2.0; extra == "dev"
Requires-Dist: pre_commit==4.0.1; extra == "dev"
Requires-Dist: tomli; extra == "dev"
Provides-Extra: example
Requires-Dist: numpy>=1.21.0; extra == "example"
Dynamic: license-file
